Proyecto_1.v

//FLipFlopD3bits

module FLipFlopD3bits(input wire [2:0] D,input wire clk,input wire reset,output [2:0] Q);
reg Q;
	always @(posedge clk or posedge reset)  
		begin
			if(reset)
				begin
					Q <= 3'b000; 
				end
			else 
				begin
					Q <= D;
				end
		end
endmodule 

module FSM_Secundario (input wire clk, reset, input wire [2:0]FS_Y, input wire [2:0]CS_Y, input wire A, G, R, N, output wire [2:0]Y);

	FLipFlopD3bits U1(FS_Y, clk, reset, CS_Y);
	
	assign FS_Y[2] = (~CS_Y[1]&~CS_Y[0]&~A&~G&~R&N);
	assign FS_Y[1] = (~CS_Y[2]&~CS_Y[0]&~A&G&~R&~N)|(~CS_Y[2]&CS_Y[1]&CS_Y[0]&~A&~G&R&~N)|(~CS_Y[2]&~CS_Y[1]&~CS_Y[0]&~A&~G&R&~N);
	assign FS_Y[0] = (~CS_Y[2]&~CS_Y[1]&A&~G&~R&~N)|(~CS_Y[2]&CS_Y[1]&CS_Y[0]&~A&~G&R&~N)|(~CS_Y[2]&~CS_Y[1]&~CS_Y[0]&~A&~G&R&~N);
	
	assign Y[2] = (~CS_Y[2]&~CS_Y[1]&~CS_Y[0]&~A&~G&~R&N);
	assign Y[1] = (~CS_Y[2]&~CS_Y[1]&~CS_Y[0]&~A&~G&R&~N)|(~CS_Y[2]&~CS_Y[1]&~CS_Y[0]&~A&G&~R&~N);
	assign Y[0] = (~CS_Y[2]&~CS_Y[1]&~CS_Y[0]&~A&~G&R&~N)|(~CS_Y[2]&~CS_Y[1]&~CS_Y[0]&A&~G&~R&~N);
	
endmodule

module FSM_Principal (input wire clk, reset, input wire [2:0]FS, input wire [2:0]CS, input wire [2:0]Y, input wire [1:0]B, input wire Back, Start, Mayor, output wire [4:0] Despacho, output wire [2:0] Display);

	FLipFlopD3bits U2(FS, clk, reset, CS);
	
	assign FS[2] = (CS[2]&~CS[1]&B[1]&B[0])|(CS[2]&~CS[0]&B[1]&B[0])|(~CS[2]&CS[1]&~CS[0]&~Back&Mayor)|(~CS[2]&~CS[1]&CS[0]&~Y[2]&Y[1]&Y[0])|(~CS[2]&~CS[1]&CS[0]&Y[2]&~Y[1]&~Y[0])|(CS[2]&~CS[1]&Back&Start)|(CS[2]&CS[1]&~CS[0]&~Start)|(CS[2]&~CS[1]&~Start&B[1])|(CS[2]&~CS[1]&~Start&B[0])|(CS[2]&CS[1]&~CS[0]&~B[1]&~B[0])|(CS[2]&~CS[1]&~Back&~B[1]&~B[0]);
	assign FS[1] = (CS[2]&CS[1]&~CS[0]&~Start)|(~CS[2]&~CS[1]&CS[0]&~Y[2]&~Y[1]&Y[0])|(~CS[2]&~CS[1]&CS[0]&~Y[2]&Y[1]&~Y[0])|(~CS[2]&CS[1]&~CS[0]&~Back)|(~CS[2]&CS[1]&Back&Start)|(~CS[2]&CS[1]&CS[0]&~Start&B[1])|(CS[1]&~CS[0]&~Start&Mayor&B[1])|(~CS[2]&CS[1]&CS[0]&~Start&B[0])|(CS[1]&~CS[0]&~Start&Mayor&B[0])|(~CS[2]&CS[1]&Start&B[1]&B[0])|(CS[1]&~CS[0]&Start&B[1]&B[0])|(~CS[2]&CS[1]&~Back&~B[1]&~B[0])|(CS[1]&~CS[0]&Start&~B[1]&~B[0]);
	assign FS[0] = (~CS[2]&CS[1]&CS[0]&Back)|(CS[2]&~CS[1]&CS[0]&Back)|(~CS[2]&CS[1]&CS[0]&~Start)|(CS[2]&~CS[1]&CS[0]&~Start)|(~CS[2]&~CS[1]&~CS[0]&~Back&Start)|(~CS[2]&CS[1]&Back&~Start&~Mayor)|(~CS[2]&CS[1]&CS[0]&B[1]&B[0])|(CS[2]&~CS[1]&CS[0]&B[1]&B[0])|(~CS[2]&CS[1]&CS[0]&~B[1]&~B[0])|(CS[2]&~CS[1]&CS[0]&~B[1]&~B[0])|(~CS[2]&CS[1]&Back&~Start&~B[1]&~B[0])|(CS[2]&~CS[1]&Back&~Start&~B[1]&~B[0])|(~CS[2]&~CS[1]&CS[0]&Y[2])|(~CS[2]&~CS[1]&CS[0]&~Y[0]);
	
	assign Display[2] = (CS[2]&~CS[1])|(CS[2]&~CS[0])|(CS[1]&~CS[0]&Back&Start&~Mayor);
	assign Display[1] = (~CS[2]&CS[1])|(CS[1]&~CS[0]);
	assign Display[0] = (~CS[2]&CS[0])|(~CS[1]&CS[0]);
	
	assign Despacho[4] = (CS[2]&CS[1]&~CS[0]&Start&~B[1]&B[0])|(CS[2]&~CS[1]&~Back&Start&~B[1]&B[0])|(CS[2]&CS[1]&~CS[0]&Start&B[1]&~B[0])|(CS[2]&~CS[1]&~Back&Start&B[1]&~B[0]);
	assign Despacho[3] = (CS[2]&CS[1]&~CS[0]&Start&~B[1]&B[0])|(CS[2]&CS[1]&~CS[0]&Start&B[1]&~B[0])|(~CS[2]&CS[1]&CS[0]&~Back&Start&~B[1]&B[0])|(~CS[2]&CS[1]&CS[0]&~Back&Start&B[1]&~B[0]);
	assign Despacho[2] = (~CS[2]&CS[1]&CS[0]&~Back&Start&~B[1]&B[0])|(CS[2]&~CS[1]&CS[0]&~Back&Start&~B[1]&B[0])|(~CS[2]&CS[1]&CS[0]&~Back&Start&B[1]&~B[0])|(CS[2]&~CS[1]&CS[0]&~Back&Start&B[1]&~B[0]);
	assign Despacho[1] = (CS[2]&CS[1]&~CS[0]&Start&B[1]&~B[0])|(CS[2]&~CS[1]&~Back&Start&B[1]&~B[0])|(~CS[2]&CS[1]&CS[0]&~Back&Start&B[1]&~B[0]);
	assign Despacho[0] = (CS[2]&CS[1]&~CS[0]&Start&~B[1]&B[0])|(CS[2]&~CS[1]&~Back&Start&~B[1]&B[0])|(~CS[2]&CS[1]&CS[0]&~Back&Start&~B[1]&B[0]);
	
endmodule

Proyecto_1_tb.v
module Proyecto_1_tb();

reg clk, reset, set, A, G, R, N, Back, Start, Mayor; 
reg [1:0]B;
wire [2:0]Y; wire[2:0]CS_Y; wire[2:0]FS_Y; wire [2:0]CS; wire[2:0]FS; wire[2:0]Display; wire[4:0]Despacho; 

FSM_Secundario FSM_1( clk, reset, FS_Y, CS_Y, A, G, R, N, Y);
FSM_Principal FSM_0(clk, reset, FS, CS, Y, B, Back, Start, Mayor, Despacho, Display);

initial begin
	clk=1;
	forever #5 clk = ~clk;  
end 



initial begin

	#1 $display("");
	$display("PROYECTO 1");
    $display("  CS  A  G  R  N  Back  Start  Mayor   B   Y  |  FS   Display  Despacho");
    $display("--------------------------------------------|------------------------");
    $monitor(" S%d  %d  %d  %d  %d   %d      %d      %d     %d   %d  |  S%d     %b      %b ", CS, A, G, R, N, Back, Start, Mayor, B, Y, FS, Display, Despacho);
	   
	#2  reset = 1; A = 0; G = 0; R = 0; N = 0; Back = 0; Start = 0; Mayor = 0; B = 2'b00; 
	#5 reset=1;
	
	//Prueba de que Dispensador de Bebidas de Buffet solo inicia (Pasa de S0 a S1) cuando "Start" = 1
    #10  A = 1; G = 0; R = 0; N = 0; Back = 0; Start = 0; Mayor = 0; B = 2'b00; reset=0;
    #10  A = 0; G = 1; R = 0; N = 0; Back = 0; Start = 0; Mayor = 0; B = 2'b00; 
    #10  A = 0; G = 0; R = 1; N = 0; Back = 0; Start = 0; Mayor = 0; B = 2'b00; 
    #10  A = 0; G = 0; R = 0; N = 1; Back = 0; Start = 0; Mayor = 0; B = 2'b00; 
    #10  A = 0; G = 0; R = 0; N = 0; Back = 1; Start = 0; Mayor = 0; B = 2'b00; 
    #10  A = 0; G = 0; R = 0; N = 0; Back = 0; Start = 0; Mayor = 1; B = 2'b00; 
    #10  A = 0; G = 0; R = 0; N = 0; Back = 0; Start = 0; Mayor = 0; B = 2'b01; 
	#10  A = 0; G = 0; R = 0; N = 0; Back = 0; Start = 0; Mayor = 0; B = 2'b10; 
    #10  A = 0; G = 0; R = 0; N = 0; Back = 0; Start = 0; Mayor = 0; B = 2'b11; 
    #10  A = 0; G = 0; R = 0; N = 0; Back = 0; Start = 1; Mayor = 0; B = 2'b00;
	#10  A = 0; G = 0; R = 0; N = 0; Back = 0; Start = 0; Mayor = 0; B = 2'b00; reset = 1;
	$display("");
	//Prueba de que se puede entrar a cada Sub-Menú (S2 para alcoholocas, S3 para gaseosas, S4 para rehidratantes y S5 para naturales) y regresar al Menú Principal (S1) 
    #10  A = 0; G = 0; R = 0; N = 0; Back = 0; Start = 1; Mayor = 0; B = 2'b00; reset = 0;
	#10  A = 1; G = 0; R = 0; N = 0; Back = 0; Start = 0; Mayor = 0; B = 2'b00; 
    #10  A = 0; G = 0; R = 0; N = 0; Back = 1; Start = 0; Mayor = 0; B = 2'b00; 
    #10  A = 0; G = 1; R = 0; N = 0; Back = 0; Start = 0; Mayor = 0; B = 2'b00; 
	#10  A = 0; G = 0; R = 0; N = 0; Back = 1; Start = 0; Mayor = 0; B = 2'b00;
	#10  A = 0; G = 0; R = 1; N = 0; Back = 0; Start = 0; Mayor = 0; B = 2'b00;
	#10  A = 0; G = 0; R = 0; N = 0; Back = 1; Start = 0; Mayor = 0; B = 2'b00;
	#10  A = 0; G = 0; R = 0; N = 1; Back = 0; Start = 0; Mayor = 0; B = 2'b00;
	#10  A = 0; G = 0; R = 0; N = 0; Back = 1; Start = 0; Mayor = 0; B = 2'b00;
	#10  A = 0; G = 0; R = 0; N = 0; Back = 0; Start = 0; Mayor = 0; B = 2'b00; reset = 1;
	$display("");
	//Prueba de que el Dispensador de Bebidas de Buffet solo dispensa al hacer una única selección (B=01 o B=10) y hacer que "Start" = 1
	//Prueba con Sub-Menú Gaseosas
	#10  A = 0; G = 0; R = 0; N = 0; Back = 0; Start = 1; Mayor = 0; B = 2'b00; reset = 0;
	#10  A = 0; G = 1; R = 0; N = 0; Back = 0; Start = 0; Mayor = 0; B = 2'b00;
	#10  A = 0; G = 0; R = 0; N = 0; Back = 0; Start = 0; Mayor = 0; B = 2'b01;
	#10  A = 0; G = 0; R = 0; N = 0; Back = 0; Start = 0; Mayor = 0; B = 2'b10;
	#10  A = 0; G = 0; R = 0; N = 0; Back = 0; Start = 1; Mayor = 0; B = 2'b00;
	#10  A = 0; G = 0; R = 0; N = 0; Back = 0; Start = 1; Mayor = 0; B = 2'b11;
	#10  A = 0; G = 0; R = 0; N = 0; Back = 0; Start = 1; Mayor = 0; B = 2'b01; 
	#10  A = 0; G = 0; R = 0; N = 0; Back = 0; Start = 0; Mayor = 0; B = 2'b00; reset = 1;
	//Prueba con Sub-Menú Rehidratantes
	#10  A = 0; G = 0; R = 0; N = 0; Back = 0; Start = 1; Mayor = 0; B = 2'b00; reset = 0;
	#10  A = 0; G = 0; R = 1; N = 0; Back = 0; Start = 0; Mayor = 0; B = 2'b00;
	#10  A = 0; G = 0; R = 0; N = 0; Back = 0; Start = 0; Mayor = 0; B = 2'b01;
	#10  A = 0; G = 0; R = 0; N = 0; Back = 0; Start = 0; Mayor = 0; B = 2'b10;
	#10  A = 0; G = 0; R = 0; N = 0; Back = 0; Start = 1; Mayor = 0; B = 2'b00;
	#10  A = 0; G = 0; R = 0; N = 0; Back = 0; Start = 1; Mayor = 0; B = 2'b11;
	#10  A = 0; G = 0; R = 0; N = 0; Back = 0; Start = 1; Mayor = 0; B = 2'b10; 
	#10  A = 0; G = 0; R = 0; N = 0; Back = 0; Start = 0; Mayor = 0; B = 2'b00; reset = 1;
	//Prueba con Sub-Menú Naturales
	#10  A = 0; G = 0; R = 0; N = 0; Back = 0; Start = 1; Mayor = 0; B = 2'b00; reset = 0;
	#10  A = 0; G = 0; R = 0; N = 1; Back = 0; Start = 0; Mayor = 0; B = 2'b00;
	#10  A = 0; G = 0; R = 0; N = 0; Back = 0; Start = 0; Mayor = 0; B = 2'b01;
	#10  A = 0; G = 0; R = 0; N = 0; Back = 0; Start = 0; Mayor = 0; B = 2'b10;
	#10  A = 0; G = 0; R = 0; N = 0; Back = 0; Start = 1; Mayor = 0; B = 2'b00;
	#10  A = 0; G = 0; R = 0; N = 0; Back = 0; Start = 1; Mayor = 0; B = 2'b11;
	#10  A = 0; G = 0; R = 0; N = 0; Back = 0; Start = 1; Mayor = 0; B = 2'b10; 
	#10  A = 0; G = 0; R = 0; N = 0; Back = 0; Start = 0; Mayor = 0; B = 2'b00; reset = 1;
	$display("");
	//Prueba de que el sistema no permite despachar una Bebida Alcohólica si no se presenta un DPI (Mayor=1) 
	#10  A = 0; G = 0; R = 0; N = 0; Back = 0; Start = 1; Mayor = 0; B = 2'b00; reset = 0;
	#10  A = 1; G = 0; R = 0; N = 0; Back = 0; Start = 0; Mayor = 0; B = 2'b00;
	#10  A = 0; G = 0; R = 0; N = 0; Back = 0; Start = 0; Mayor = 0; B = 2'b01;
	#10  A = 0; G = 0; R = 0; N = 0; Back = 0; Start = 0; Mayor = 0; B = 2'b10;
	#10  A = 0; G = 0; R = 0; N = 0; Back = 0; Start = 1; Mayor = 0; B = 2'b00;
	#10  A = 0; G = 0; R = 0; N = 0; Back = 0; Start = 1; Mayor = 0; B = 2'b11;
	#10  A = 0; G = 0; R = 0; N = 0; Back = 0; Start = 1; Mayor = 0; B = 2'b10;
	#10  A = 0; G = 0; R = 0; N = 0; Back = 0; Start = 0; Mayor = 1; B = 2'b00;
	#10  A = 0; G = 0; R = 0; N = 0; Back = 0; Start = 0; Mayor = 0; B = 2'b00;
	#10  A = 0; G = 0; R = 0; N = 0; Back = 0; Start = 0; Mayor = 0; B = 2'b01;
	#10  A = 0; G = 0; R = 0; N = 0; Back = 0; Start = 0; Mayor = 0; B = 2'b10;
	#10  A = 0; G = 0; R = 0; N = 0; Back = 0; Start = 1; Mayor = 0; B = 2'b00;
	#10  A = 0; G = 0; R = 0; N = 0; Back = 0; Start = 1; Mayor = 0; B = 2'b11;
	#10  A = 0; G = 0; R = 0; N = 0; Back = 0; Start = 1; Mayor = 0; B = 2'b01; 
	#10  A = 0; G = 0; R = 0; N = 0; Back = 0; Start = 0; Mayor = 0; B = 2'b00; 
	
	//#10  A = 0; G = 0; R = 0; N = 0; Back = 0; Start = 0; Mayor = 0; B = 2'b00;	
	
	#10 $display("");
 end
	
initial
#630 $finish; 
 

initial begin
    $dumpfile("Proyecto_1_tb.vcd");
    $dumpvars(0, Proyecto_1_tb);
end

endmodule

Proyecto_1_tb.vcd
$date
	Sat Oct 10 20:10:22 2020
$end
$version
	Icarus Verilog
$end
$timescale
	1ps
$end
$scope module Proyecto_1_tb $end
$var wire 3 ! Y [2:0] $end
$var wire 3 " FS_Y [2:0] $end
$var wire 3 # FS [2:0] $end
$var wire 3 $ Display [2:0] $end
$var wire 5 % Despacho [4:0] $end
$var wire 3 & CS_Y [2:0] $end
$var wire 3 ' CS [2:0] $end
$var reg 1 ( A $end
$var reg 2 ) B [1:0] $end
$var reg 1 * Back $end
$var reg 1 + G $end
$var reg 1 , Mayor $end
$var reg 1 - N $end
$var reg 1 . R $end
$var reg 1 / Start $end
$var reg 1 0 clk $end
$var reg 1 1 reset $end
$scope module FSM_0 $end
$var wire 2 2 B [1:0] $end
$var wire 1 * Back $end
$var wire 1 , Mayor $end
$var wire 1 / Start $end
$var wire 1 0 clk $end
$var wire 1 1 reset $end
$var wire 3 3 Y [2:0] $end
$var wire 3 4 FS [2:0] $end
$var wire 3 5 Display [2:0] $end
$var wire 5 6 Despacho [4:0] $end
$var wire 3 7 CS [2:0] $end
$scope module U2 $end
$var wire 3 8 D [2:0] $end
$var wire 1 0 clk $end
$var wire 1 1 reset $end
$var reg 3 9 Q [2:0] $end
$upscope $end
$upscope $end
$scope module FSM_1 $end
$var wire 1 ( A $end
$var wire 1 + G $end
$var wire 1 - N $end
$var wire 1 . R $end
$var wire 1 0 clk $end
$var wire 1 1 reset $end
$var wire 3 : Y [2:0] $end
$var wire 3 ; FS_Y [2:0] $end
$var wire 3 < CS_Y [2:0] $end
$scope module U1 $end
$var wire 3 = D [2:0] $end
$var wire 1 0 clk $end
$var wire 1 1 reset $end
$var reg 3 > Q [2:0] $end
$upscope $end
$upscope $end
$upscope $end
$enddefinitions $end
#0
$dumpvars
bx >
bx =
bx <
bx ;
bx :
bx 9
bx 8
bx 7
bx 6
bx 5
bx 4
bx 3
bx 2
x1
10
x/
x.
x-
x,
x+
x*
bx )
x(
bx '
bx &
bx %
bx $
bx #
bx "
bx !
$end
#3
b0 #
b0 4
b0 8
b0 $
b0 5
b0 '
b0 7
b0 9
b0 &
b0 <
b0 >
b0 %
b0 6
b0 "
b0 ;
b0 =
b0 !
b0 3
b0 :
b0 )
b0 2
0,
0/
0*
0-
0.
0+
0(
11
#5
00
#10
10
#15
00
#18
b1 "
b1 ;
b1 =
b1 !
b1 3
b1 :
01
1(
#20
b0 !
b0 3
b0 :
b1 &
b1 <
b1 >
10
#25
00
#28
b0 "
b0 ;
b0 =
1+
0(
#30
b10 "
b10 ;
b10 =
b10 !
b10 3
b10 :
b0 &
b0 <
b0 >
10
#35
00
#38
b11 "
b11 ;
b11 =
b11 !
b11 3
b11 :
1.
0+
#40
b0 !
b0 3
b0 :
b11 &
b11 <
b11 >
10
#45
00
#48
b0 "
b0 ;
b0 =
1-
0.
#50
b100 !
b100 3
b100 :
b100 "
b100 ;
b100 =
b0 &
b0 <
b0 >
10
#55
00
#58
b0 "
b0 ;
b0 =
b0 !
b0 3
b0 :
1*
0-
#60
10
#65
00
#68
1,
0*
#70
10
#75
00
#78
b1 )
b1 2
0,
#80
10
#85
00
#88
b10 )
b10 2
#90
10
#95
00
#98
b11 )
b11 2
#100
10
#105
00
#108
b1 #
b1 4
b1 8
b0 )
b0 2
1/
#110
b1 $
b1 5
b1 '
b1 7
b1 9
10
#115
00
#118
b0 #
b0 4
b0 8
b0 $
b0 5
b0 '
b0 7
b0 9
11
0/
#120
10
#125
00
#128
b1 #
b1 4
b1 8
01
1/
#130
b1 $
b1 5
b1 '
b1 7
b1 9
10
#135
00
#138
b10 #
b10 4
b10 8
b1 "
b1 ;
b1 =
b1 !
b1 3
b1 :
0/
1(
#140
b0 !
b0 3
b0 :
b10 $
b10 5
b1 &
b1 <
b1 >
b10 '
b10 7
b10 9
10
#145
00
#148
b1 #
b1 4
b1 8
b0 "
b0 ;
b0 =
1*
0(
#150
b1 $
b1 5
b1 '
b1 7
b1 9
b0 &
b0 <
b0 >
10
#155
00
#158
b11 #
b11 4
b11 8
b10 "
b10 ;
b10 =
b10 !
b10 3
b10 :
0*
1+
#160
b0 !
b0 3
b0 :
b11 #
b11 4
b11 8
b11 $
b11 5
b10 &
b10 <
b10 >
b11 '
b11 7
b11 9
10
#165
00
#168
b1 #
b1 4
b1 8
b0 "
b0 ;
b0 =
1*
0+
#170
b1 $
b1 5
b1 '
b1 7
b1 9
b0 &
b0 <
b0 >
10
#175
00
#178
b100 #
b100 4
b100 8
b11 "
b11 ;
b11 =
b11 !
b11 3
b11 :
0*
1.
#180
b0 !
b0 3
b0 :
b100 $
b100 5
b11 &
b11 <
b11 >
b100 '
b100 7
b100 9
10
#185
00
#188
b1 #
b1 4
b1 8
b0 "
b0 ;
b0 =
1*
0.
#190
b1 $
b1 5
b1 '
b1 7
b1 9
b0 &
b0 <
b0 >
10
#195
00
#198
b101 #
b101 4
b101 8
b100 "
b100 ;
b100 =
b100 !
b100 3
b100 :
0*
1-
#200
b0 !
b0 3
b0 :
b101 #
b101 4
b101 8
b101 $
b101 5
b100 &
b100 <
b100 >
b101 '
b101 7
b101 9
10
#205
00
#208
b1 #
b1 4
b1 8
b0 "
b0 ;
b0 =
1*
0-
#210
b1 $
b1 5
b1 '
b1 7
b1 9
b0 &
b0 <
b0 >
10
#215
00
#218
b0 #
b0 4
b0 8
b0 $
b0 5
b0 '
b0 7
b0 9
11
0*
#220
10
#225
00
#228
b1 #
b1 4
b1 8
01
1/
#230
b1 $
b1 5
b1 '
b1 7
b1 9
10
#235
00
#238
b11 #
b11 4
b11 8
b10 "
b10 ;
b10 =
b10 !
b10 3
b10 :
0/
1+
#240
b0 !
b0 3
b0 :
b11 #
b11 4
b11 8
b11 $
b11 5
b11 '
b11 7
b11 9
b10 &
b10 <
b10 >
10
#245
00
#248
b11 #
b11 4
b11 8
b0 "
b0 ;
b0 =
b1 )
b1 2
0+
#250
b0 &
b0 <
b0 >
10
#255
00
#258
b11 #
b11 4
b11 8
b10 )
b10 2
#260
10
#265
00
#268
b0 )
b0 2
1/
#270
10
#275
00
#278
b11 #
b11 4
b11 8
b0 %
b0 6
b11 )
b11 2
#280
10
#285
00
#288
b0 #
b0 4
b0 8
b1101 %
b1101 6
b1 )
b1 2
#290
b1 #
b1 4
b1 8
b0 %
b0 6
b0 $
b0 5
b0 '
b0 7
b0 9
10
#295
00
#298
b0 #
b0 4
b0 8
11
b0 )
b0 2
0/
#300
10
#305
00
#308
b1 #
b1 4
b1 8
01
1/
#310
b1 $
b1 5
b1 '
b1 7
b1 9
10
#315
00
#318
b100 #
b100 4
b100 8
b11 "
b11 ;
b11 =
b11 !
b11 3
b11 :
0/
1.
#320
b0 !
b0 3
b0 :
b100 $
b100 5
b11 &
b11 <
b11 >
b100 '
b100 7
b100 9
10
#325
00
#328
b100 #
b100 4
b100 8
b0 "
b0 ;
b0 =
b1 )
b1 2
0.
#330
b0 &
b0 <
b0 >
10
#335
00
#338
b100 #
b100 4
b100 8
b10 )
b10 2
#340
10
#345
00
#348
b0 )
b0 2
1/
#350
10
#355
00
#358
b100 #
b100 4
b100 8
b0 %
b0 6
b11 )
b11 2
#360
10
#365
00
#368
b0 #
b0 4
b0 8
b10010 %
b10010 6
b10 )
b10 2
#370
b1 #
b1 4
b1 8
b0 %
b0 6
b0 $
b0 5
b0 '
b0 7
b0 9
10
#375
00
#378
b0 #
b0 4
b0 8
11
b0 )
b0 2
0/
#380
10
#385
00
#388
b1 #
b1 4
b1 8
01
1/
#390
b1 $
b1 5
b1 '
b1 7
b1 9
10
#395
00
#398
b101 #
b101 4
b101 8
b100 "
b100 ;
b100 =
b100 !
b100 3
b100 :
0/
1-
#400
b0 !
b0 3
b0 :
b101 #
b101 4
b101 8
b101 $
b101 5
b101 '
b101 7
b101 9
b100 &
b100 <
b100 >
10
#405
00
#408
b101 #
b101 4
b101 8
b0 "
b0 ;
b0 =
b1 )
b1 2
0-
#410
b0 &
b0 <
b0 >
10
#415
00
#418
b101 #
b101 4
b101 8
b10 )
b10 2
#420
10
#425
00
#428
b0 )
b0 2
1/
#430
10
#435
00
#438
b101 #
b101 4
b101 8
b0 %
b0 6
b11 )
b11 2
#440
10
#445
00
#448
b0 #
b0 4
b0 8
b10110 %
b10110 6
b10 )
b10 2
#450
b1 #
b1 4
b1 8
b0 %
b0 6
b0 $
b0 5
b0 '
b0 7
b0 9
10
#455
00
#458
b0 #
b0 4
b0 8
11
b0 )
b0 2
0/
#460
10
#465
00
#468
b1 #
b1 4
b1 8
01
1/
#470
b1 $
b1 5
b1 '
b1 7
b1 9
10
#475
00
#478
b10 #
b10 4
b10 8
b1 "
b1 ;
b1 =
b1 !
b1 3
b1 :
0/
1(
#480
b0 !
b0 3
b0 :
b10 $
b10 5
b1 &
b1 <
b1 >
b10 '
b10 7
b10 9
10
#485
00
#488
b0 "
b0 ;
b0 =
b1 )
b1 2
0(
#490
b0 &
b0 <
b0 >
10
#495
00
#498
b10 )
b10 2
#500
10
#505
00
#508
b0 )
b0 2
1/
#510
10
#515
00
#518
b11 )
b11 2
#520
10
#525
00
#528
b10 )
b10 2
#530
10
#535
00
#538
b110 #
b110 4
b110 8
b0 )
b0 2
1,
0/
#540
b110 $
b110 5
b110 '
b110 7
b110 9
10
#545
00
#548
0,
#550
10
#555
00
#558
b1 )
b1 2
#560
10
#565
00
#568
b10 )
b10 2
#570
10
#575
00
#578
b0 )
b0 2
1/
#580
10
#585
00
#588
b110 #
b110 4
b110 8
b0 %
b0 6
b11 )
b11 2
#590
10
#595
00
#598
b0 #
b0 4
b0 8
b11001 %
b11001 6
b1 )
b1 2
#600
b1 #
b1 4
b1 8
b0 %
b0 6
b0 $
b0 5
b0 '
b0 7
b0 9
10
#605
00
#608
b0 #
b0 4
b0 8
b0 )
b0 2
0/
